<?xml version="1.0" encoding="UTF-8"?>
<!--
 MAEC Package Polymorphic Family Example
 -Demonstrates how MAEC can capture basic polymorphic
  behavior associated with a malware family
 -Based on real Zeus v1.x binaries and dynamic analysis results
 
 Created February 2015 for MAEC v4.1 and CybOX v2.1-->
<maecPackage:MAEC_Package
 xmlns:maecPackage="http://maec.mitre.org/XMLSchema/maec-package-2"
 xmlns:maecBundle="http://maec.mitre.org/XMLSchema/maec-bundle-4"
 xmlns:maecVocabs="http://maec.mitre.org/default_vocabularies-1"
 xmlns:cybox="http://docs.oasis-open.org/cti/ns/cybox/core-2"
 xmlns:cyboxCommon="http://docs.oasis-open.org/cti/ns/cybox/common-2"
 xmlns:cyboxVocabs="http://docs.oasis-open.org/cti/ns/cybox/vocabularies-2"
 xmlns:FileObj="http://docs.oasis-open.org/cti/ns/cybox/objects/file-2"
 xmlns:WinExecutableFileObj="http://docs.oasis-open.org/cti/ns/cybox/objects/win-executable-file-2"
 xmlns:WinRegistryKeyObj="http://docs.oasis-open.org/cti/ns/cybox/objects/win-registry-key-2"
 xmlns:xsi="http://www.w3.org/2001/XMLSchema-instance"
 xmlns:example="http://example.com"
 xsi:schemaLocation="http://maec.mitre.org/XMLSchema/maec-package-2 http://maec.mitre.org/language/version4.1/maec_package_schema.xsd
 http://maec.mitre.org/default_vocabularies-1 http://maec.mitre.org/language/version4.1/maec_default_vocabularies.xsd
 http://docs.oasis-open.org/cti/ns/cybox/vocabularies-2 http://docs.oasis-open.org/cti/cybox/v2.1.1/csd01/xml-schemas/default-vocabularies.xsd
 http://cybox.mitre.org/objects#WinExecutableFileObject http://docs.oasis-open.org/cti/cybox/v2.1.1/csd01/xml-schemas/objects/Win-Executable-File-Object.xsd
 http://docs.oasis-open.org/cti/ns/cybox/objects/win-registry-key-2 http://docs.oasis-open.org/cti/cybox/v2.1.1/csd01/xml-schemas/objects/Win-Registry-Key-Object.xsd" 
 id="example:package-e7597272-4c5d-40ef-be1d-481ffd451fe8" schema_version="2.1">
    <maecPackage:Malware_Subjects>
        <maecPackage:Malware_Subject id="example:subject-eb54999d-4a5a-439d-aeb9-39b5f7eaf77c">
            <maecPackage:Malware_Instance_Object_Attributes>
                <cybox:Properties xsi:type="WinExecutableFileObj:WindowsExecutableFileObjectType">
                    <FileObj:Hashes>
                        <cyboxCommon:Hash>
                            <cyboxCommon:Type xsi:type="cyboxVocabs:HashNameVocab-1.0">MD5</cyboxCommon:Type>
                            <cyboxCommon:Simple_Hash_Value>076e5b2bae0b4b3a3d81c85610b95cd4</cyboxCommon:Simple_Hash_Value>
                        </cyboxCommon:Hash>
                    </FileObj:Hashes>
                </cybox:Properties>
            </maecPackage:Malware_Instance_Object_Attributes>
            <maecPackage:Findings_Bundles>
                <maecPackage:Bundle id="example:bundle-a8fa8e15-ed98-4124-ae11-336f04b9e241" defined_subject="false" schema_version="4.1">
                    <maecBundle:Behaviors>
                        <maecBundle:Behavior id="example:behavior-1127c9d9-2ab0-4763-a53b-46145425bdf5">
                            <maecBundle:Description>Autostart via Windows registry</maecBundle:Description>
                            <maecBundle:Action_Composition>
                                <maecBundle:Action_Reference action_id="example:action-0b8623b5-5264-4ae8-a2ed-20dbf51558b4" behavioral_ordering="1"/>
                                <maecBundle:Action_Reference action_id="example:action-f853f0bf-033b-4d2d-b927-702bb9cf6e8d" behavioral_ordering="2"/>
                            </maecBundle:Action_Composition>
                        </maecBundle:Behavior>
                    </maecBundle:Behaviors>
                    <maecBundle:Actions>
                        <maecBundle:Action id="example:action-0b8623b5-5264-4ae8-a2ed-20dbf51558b4">
                            <cybox:Name xsi:type="maecVocabs:FileActionNameVocab-1.1">create file</cybox:Name>
                            <cybox:Associated_Objects>
                                <cybox:Associated_Object>
                                    <cybox:Properties xsi:type="WinExecutableFileObj:WindowsExecutableFileObjectType">
                                        <FileObj:File_Path>C:\WINDOWS\system32\oembios.exe</FileObj:File_Path>
                                    </cybox:Properties>
                                    <cybox:Association_Type xsi:type="maecVocabs:ActionObjectAssociationTypeVocab-1.0">output</cybox:Association_Type>
                                </cybox:Associated_Object>
                            </cybox:Associated_Objects>
                        </maecBundle:Action>
                        <maecBundle:Action id="example:action-f853f0bf-033b-4d2d-b927-702bb9cf6e8d">
                            <cybox:Name xsi:type="maecVocabs:RegistryActionNameVocab-1.0">modify registry key value</cybox:Name>
                            <cybox:Associated_Objects>
                                <cybox:Associated_Object>
                                    <cybox:Properties xsi:type="WinRegistryKeyObj:WindowsRegistryKeyObjectType">
                                        <WinRegistryKeyObj:Key>software\microsoft\windows nt\currentversion\winlogon</WinRegistryKeyObj:Key>
                                        <WinRegistryKeyObj:Hive>HKEY_LOCAL_MACHINE</WinRegistryKeyObj:Hive>
                                        <WinRegistryKeyObj:Values>
                                            <WinRegistryKeyObj:Value>
                                                <WinRegistryKeyObj:Name>userinit</WinRegistryKeyObj:Name>
                                                <WinRegistryKeyObj:Data>C:\WINDOWS\system32\userinit.exe,C:\WINDOWS\system32\oembios.exe,</WinRegistryKeyObj:Data>
                                            </WinRegistryKeyObj:Value>
                                        </WinRegistryKeyObj:Values>
                                    </cybox:Properties>
                                    <cybox:Association_Type xsi:type="maecVocabs:ActionObjectAssociationTypeVocab-1.0">output</cybox:Association_Type>
                                </cybox:Associated_Object>
                            </cybox:Associated_Objects>
                        </maecBundle:Action>
                    </maecBundle:Actions>
                </maecPackage:Bundle>
            </maecPackage:Findings_Bundles>
        </maecPackage:Malware_Subject>
        
        <maecPackage:Malware_Subject id="example:subject-0b1b98d8-9235-427d-aeab-54bdf9f70412">
            <maecPackage:Malware_Instance_Object_Attributes>
                <cybox:Properties xsi:type="WinExecutableFileObj:WindowsExecutableFileObjectType">
                    <FileObj:Hashes>
                        <cyboxCommon:Hash>
                            <cyboxCommon:Type xsi:type="cyboxVocabs:HashNameVocab-1.0">MD5</cyboxCommon:Type>
                            <cyboxCommon:Simple_Hash_Value>0efade6825e49cf0cf9c87695d466157</cyboxCommon:Simple_Hash_Value>
                        </cyboxCommon:Hash>
                    </FileObj:Hashes>
                </cybox:Properties>
            </maecPackage:Malware_Instance_Object_Attributes>
            <maecPackage:Findings_Bundles>
                <maecPackage:Bundle id="example:bundle-92f9f870-1fae-40a6-9d60-71b7efb48ea3" defined_subject="false" schema_version="4.1">
                    <maecBundle:Behaviors>
                        <maecBundle:Behavior id="example:behavior-1b75ce50-d6f6-49a4-9524-9b15fa2f7d49">
                            <maecBundle:Description>Autostart via Windows registry</maecBundle:Description>
                            <maecBundle:Action_Composition>
                                <maecBundle:Action_Reference action_id="example:action-8bb139fc-1244-4b67-a652-6e01f1da8576" behavioral_ordering="1"/>
                                <maecBundle:Action_Reference action_id="example:action-877637cf-4a80-4984-8172-3fccb777edf4" behavioral_ordering="2"/>
                            </maecBundle:Action_Composition>
                        </maecBundle:Behavior>
                    </maecBundle:Behaviors>
                    <maecBundle:Actions>
                        <maecBundle:Action id="example:action-8bb139fc-1244-4b67-a652-6e01f1da8576">
                            <cybox:Name xsi:type="maecVocabs:FileActionNameVocab-1.1">create file</cybox:Name>
                            <cybox:Associated_Objects>
                                <cybox:Associated_Object>
                                    <cybox:Properties xsi:type="WinExecutableFileObj:WindowsExecutableFileObjectType">
                                        <FileObj:File_Path>C:\WINDOWS\system32\ntos.exe</FileObj:File_Path>
                                    </cybox:Properties>
                                    <cybox:Association_Type xsi:type="maecVocabs:ActionObjectAssociationTypeVocab-1.0">output</cybox:Association_Type>
                                </cybox:Associated_Object>
                            </cybox:Associated_Objects>
                        </maecBundle:Action>
                        <maecBundle:Action id="example:action-877637cf-4a80-4984-8172-3fccb777edf4">
                            <cybox:Name xsi:type="maecVocabs:RegistryActionNameVocab-1.0">modify registry key value</cybox:Name>
                            <cybox:Associated_Objects>
                                <cybox:Associated_Object>
                                    <cybox:Properties xsi:type="WinRegistryKeyObj:WindowsRegistryKeyObjectType">
                                        <WinRegistryKeyObj:Key>software\microsoft\windows nt\currentversion\winlogon</WinRegistryKeyObj:Key>
                                        <WinRegistryKeyObj:Hive>HKEY_LOCAL_MACHINE</WinRegistryKeyObj:Hive>
                                        <WinRegistryKeyObj:Values>
                                            <WinRegistryKeyObj:Value>
                                                <WinRegistryKeyObj:Name>userinit</WinRegistryKeyObj:Name>
                                                <WinRegistryKeyObj:Data>C:\WINDOWS\system32\userinit.exe,C:\WINDOWS\system32\ntos.exe,</WinRegistryKeyObj:Data>
                                            </WinRegistryKeyObj:Value>
                                        </WinRegistryKeyObj:Values>
                                    </cybox:Properties>
                                    <cybox:Association_Type xsi:type="maecVocabs:ActionObjectAssociationTypeVocab-1.0">output</cybox:Association_Type>
                                </cybox:Associated_Object>
                            </cybox:Associated_Objects>
                        </maecBundle:Action>
                    </maecBundle:Actions>
                </maecPackage:Bundle>
            </maecPackage:Findings_Bundles>
        </maecPackage:Malware_Subject>
        
        <maecPackage:Malware_Subject id="example:subject-9fb155a9-abc7-4d38-8dc4-df00f83732f7">
            <maecPackage:Malware_Instance_Object_Attributes>
                <cybox:Properties xsi:type="WinExecutableFileObj:WindowsExecutableFileObjectType">
                    <FileObj:Hashes>
                        <cyboxCommon:Hash>
                            <cyboxCommon:Type xsi:type="cyboxVocabs:HashNameVocab-1.0">MD5</cyboxCommon:Type>
                            <cyboxCommon:Simple_Hash_Value>3dec61e0480eb79d2041605444437fee</cyboxCommon:Simple_Hash_Value>
                        </cyboxCommon:Hash>
                    </FileObj:Hashes>
                </cybox:Properties>
            </maecPackage:Malware_Instance_Object_Attributes>
            <maecPackage:Findings_Bundles>
                <maecPackage:Bundle id="example:bundle-ff450404-5db5-453b-8dc3-63cefd1a00c8" defined_subject="false" schema_version="4.1">
                    <maecBundle:Behaviors>
                        <maecBundle:Behavior id="example:behavior-f085f3b9-9939-4ac9-9445-bc4b61fec981">
                            <maecBundle:Description>Autostart via Windows registry</maecBundle:Description>
                            <maecBundle:Action_Composition>
                                <maecBundle:Action_Reference action_id="example:action-f49292ee-8ee6-4eb0-a744-295da612556c" behavioral_ordering="1"/>
                                <maecBundle:Action_Reference action_id="example:action-7504a917-d264-46d8-b55a-a9d4c214ce23" behavioral_ordering="2"/>
                            </maecBundle:Action_Composition>
                        </maecBundle:Behavior>
                    </maecBundle:Behaviors>
                    <maecBundle:Actions>
                        <maecBundle:Action id="example:action-f49292ee-8ee6-4eb0-a744-295da612556c">
                            <cybox:Name xsi:type="maecVocabs:FileActionNameVocab-1.1">create file</cybox:Name>
                            <cybox:Associated_Objects>
                                <cybox:Associated_Object>
                                    <cybox:Properties xsi:type="WinExecutableFileObj:WindowsExecutableFileObjectType">
                                        <FileObj:File_Path>C:\WINDOWS\system32\twext.exe</FileObj:File_Path>
                                    </cybox:Properties>
                                    <cybox:Association_Type xsi:type="maecVocabs:ActionObjectAssociationTypeVocab-1.0">output</cybox:Association_Type>
                                </cybox:Associated_Object>
                            </cybox:Associated_Objects>
                        </maecBundle:Action>
                        <maecBundle:Action id="example:action-7504a917-d264-46d8-b55a-a9d4c214ce23">
                            <cybox:Name xsi:type="maecVocabs:RegistryActionNameVocab-1.0">modify registry key value</cybox:Name>
                            <cybox:Associated_Objects>
                                <cybox:Associated_Object>
                                    <cybox:Properties xsi:type="WinRegistryKeyObj:WindowsRegistryKeyObjectType">
                                        <WinRegistryKeyObj:Key>software\microsoft\windows nt\currentversion\winlogon</WinRegistryKeyObj:Key>
                                        <WinRegistryKeyObj:Hive>HKEY_LOCAL_MACHINE</WinRegistryKeyObj:Hive>
                                        <WinRegistryKeyObj:Values>
                                            <WinRegistryKeyObj:Value>
                                                <WinRegistryKeyObj:Name>userinit</WinRegistryKeyObj:Name>
                                                <WinRegistryKeyObj:Data>C:\WINDOWS\system32\userinit.exe,C:\WINDOWS\system32\twext.exe,</WinRegistryKeyObj:Data>
                                            </WinRegistryKeyObj:Value>
                                        </WinRegistryKeyObj:Values>
                                    </cybox:Properties>
                                    <cybox:Association_Type xsi:type="maecVocabs:ActionObjectAssociationTypeVocab-1.0">output</cybox:Association_Type>
                                </cybox:Associated_Object>
                            </cybox:Associated_Objects>
                        </maecBundle:Action>
                    </maecBundle:Actions>
                </maecPackage:Bundle>
            </maecPackage:Findings_Bundles>
        </maecPackage:Malware_Subject>
        
        <maecPackage:Malware_Subject id="example:subject-662d7a32-2246-4712-8dae-f201dac945b3">
            <maecPackage:Malware_Instance_Object_Attributes>
                <cybox:Properties xsi:type="WinExecutableFileObj:WindowsExecutableFileObjectType">
                    <FileObj:Hashes>
                        <cyboxCommon:Hash>
                            <cyboxCommon:Type xsi:type="cyboxVocabs:HashNameVocab-1.0">MD5</cyboxCommon:Type>
                            <cyboxCommon:Simple_Hash_Value>78bcf2bfd658f7b3475eb4746059289e</cyboxCommon:Simple_Hash_Value>
                        </cyboxCommon:Hash>
                    </FileObj:Hashes>
                </cybox:Properties>
            </maecPackage:Malware_Instance_Object_Attributes>
            <maecPackage:Findings_Bundles>
                <maecPackage:Bundle id="example:bundle-0e58c97f-91dc-4c47-ae2d-8e56fcc248fb" defined_subject="false" schema_version="4.1">
                    <maecBundle:Behaviors>
                        <maecBundle:Behavior id="example:behavior-0c226f00-f6ed-4246-a203-5b574cac3362">
                            <maecBundle:Description>Autostart via Windows registry</maecBundle:Description>
                            <maecBundle:Action_Composition>
                                <maecBundle:Action_Reference action_id="example:action-5f32221a-54b0-4364-9e9b-d7ecaf29a75a" behavioral_ordering="1"/>
                                <maecBundle:Action_Reference action_id="example:action-ada5af3f-0dd5-4a7b-92d1-2c146d8fe100" behavioral_ordering="2"/>
                            </maecBundle:Action_Composition>
                        </maecBundle:Behavior>
                    </maecBundle:Behaviors>
                    <maecBundle:Actions>
                        <maecBundle:Action id="example:action-5f32221a-54b0-4364-9e9b-d7ecaf29a75a">
                            <cybox:Name xsi:type="maecVocabs:FileActionNameVocab-1.1">create file</cybox:Name>
                            <cybox:Associated_Objects>
                                <cybox:Associated_Object>
                                    <cybox:Properties xsi:type="WinExecutableFileObj:WindowsExecutableFileObjectType">
                                        <FileObj:File_Path>C:\WINDOWS\system32\sdra64.exe</FileObj:File_Path>
                                    </cybox:Properties>
                                    <cybox:Association_Type xsi:type="maecVocabs:ActionObjectAssociationTypeVocab-1.0">output</cybox:Association_Type>
                                </cybox:Associated_Object>
                            </cybox:Associated_Objects>
                        </maecBundle:Action>
                        <maecBundle:Action id="example:action-ada5af3f-0dd5-4a7b-92d1-2c146d8fe100">
                            <cybox:Name xsi:type="maecVocabs:RegistryActionNameVocab-1.0">modify registry key value</cybox:Name>
                            <cybox:Associated_Objects>
                                <cybox:Associated_Object>
                                    <cybox:Properties xsi:type="WinRegistryKeyObj:WindowsRegistryKeyObjectType">
                                        <WinRegistryKeyObj:Key>software\microsoft\windows nt\currentversion\winlogon</WinRegistryKeyObj:Key>
                                        <WinRegistryKeyObj:Hive>HKEY_LOCAL_MACHINE</WinRegistryKeyObj:Hive>
                                        <WinRegistryKeyObj:Values>
                                            <WinRegistryKeyObj:Value>
                                                <WinRegistryKeyObj:Name>userinit</WinRegistryKeyObj:Name>
                                                <WinRegistryKeyObj:Data>C:\WINDOWS\system32\userinit.exe,C:\WINDOWS\system32\sdra64.exe,</WinRegistryKeyObj:Data>
                                            </WinRegistryKeyObj:Value>
                                        </WinRegistryKeyObj:Values>
                                    </cybox:Properties>
                                    <cybox:Association_Type xsi:type="maecVocabs:ActionObjectAssociationTypeVocab-1.0">output</cybox:Association_Type>
                                </cybox:Associated_Object>
                            </cybox:Associated_Objects>
                        </maecBundle:Action>
                    </maecBundle:Actions>
                </maecPackage:Bundle>
            </maecPackage:Findings_Bundles>
        </maecPackage:Malware_Subject>
    </maecPackage:Malware_Subjects>
    
    <maecPackage:Grouping_Relationships>
        <maecPackage:Grouping_Relationship>
            <maecPackage:Type xsi:type="maecVocabs:GroupingRelationshipTypeVocab-1.0">same malware family</maecPackage:Type>
            <maecPackage:Malware_Family_Name>Zeus 1.x</maecPackage:Malware_Family_Name>
        </maecPackage:Grouping_Relationship>
    </maecPackage:Grouping_Relationships>
</maecPackage:MAEC_Package>
